travelpurpose/__init__.py
travelpurpose/classifier.py
travelpurpose/cli.py
travelpurpose/tags.py
travelpurpose/data/cities.json
travelpurpose/data/cities_enhanced.json
travelpurpose/data/wikidata_cities_cache.json
travelpurpose/ontology/mapping_nbd.yaml
travelpurpose/ontology/ontology.yaml
travelpurpose/utils/__init__.py
travelpurpose/utils/agoda.py
travelpurpose/utils/booking.py
travelpurpose/utils/geonames.py
travelpurpose/utils/harvest.py
travelpurpose/utils/io.py
travelpurpose/utils/kayak.py
travelpurpose/utils/normalize.py
travelpurpose/utils/opentripmap.py
travelpurpose/utils/restcountries.py
travelpurpose/utils/scoring.py
travelpurpose/utils/skyscanner.py
travelpurpose/utils/tripdotcom.py
travelpurpose/utils/trivago.py
travelpurpose/utils/wikidata.py
travelpurpose-0.2.4.dist-info/licenses/LICENSE
travelpurpose-0.2.4.dist-info/METADATA
travelpurpose-0.2.4.dist-info/WHEEL
travelpurpose-0.2.4.dist-info/entry_points.txt
travelpurpose-0.2.4.dist-info/top_level.txt
travelpurpose-0.2.4.dist-info/RECORD
