Metadata-Version: 2.4
Name: travelpurpose
Version: 0.2.4
Summary: Production-grade library for classifying world cities by travel purpose using multi-source data
Author-email: Teyfik OZ <teyfikoz@example.com>
License: MIT
Project-URL: Homepage, https://github.com/teyfikoz/Travel_Purpose-City_Tags
Project-URL: Documentation, https://github.com/teyfikoz/Travel_Purpose-City_Tags#readme
Project-URL: Repository, https://github.com/teyfikoz/Travel_Purpose-City_Tags
Project-URL: Bug Tracker, https://github.com/teyfikoz/Travel_Purpose-City_Tags/issues
Keywords: travel,city,classification,tourism,purpose,tags,data-engineering
Classifier: Development Status :: 4 - Beta
Classifier: Intended Audience :: Developers
Classifier: Intended Audience :: Science/Research
Classifier: License :: OSI Approved :: MIT License
Classifier: Programming Language :: Python :: 3
Classifier: Programming Language :: Python :: 3.10
Classifier: Programming Language :: Python :: 3.11
Classifier: Programming Language :: Python :: 3.12
Classifier: Topic :: Scientific/Engineering :: Information Analysis
Classifier: Topic :: Software Development :: Libraries :: Python Modules
Requires-Python: >=3.10
License-File: LICENSE
Requires-Dist: pandas>=2.0.0
Requires-Dist: numpy>=1.24.0
Requires-Dist: pyarrow>=12.0.0
Requires-Dist: pyyaml>=6.0
Requires-Dist: requests>=2.31.0
Requires-Dist: requests-cache>=1.1.0
Requires-Dist: beautifulsoup4>=4.12.0
Requires-Dist: lxml>=4.9.0
Requires-Dist: pydantic>=2.0.0
Requires-Dist: typer>=0.9.0
Requires-Dist: rich>=13.0.0
Requires-Dist: tqdm>=4.65.0
Requires-Dist: sentence-transformers>=2.2.0
Requires-Dist: scikit-learn>=1.3.0
Requires-Dist: openpyxl>=3.1.0
Requires-Dist: SPARQLWrapper>=2.0.0
Requires-Dist: urllib3>=2.0.0
Requires-Dist: playwright>=1.40.0
Provides-Extra: dev
Requires-Dist: pytest>=7.4.0; extra == "dev"
Requires-Dist: pytest-cov>=4.1.0; extra == "dev"
Requires-Dist: ruff>=0.1.0; extra == "dev"
Requires-Dist: mypy>=1.5.0; extra == "dev"
Requires-Dist: black>=23.0.0; extra == "dev"
Requires-Dist: jupyterlab>=4.0.0; extra == "dev"
Requires-Dist: notebook>=7.0.0; extra == "dev"
Dynamic: license-file
